odoo/addons/mail_activity_board/README.rst
odoo/addons/mail_activity_board/__init__.py
odoo/addons/mail_activity_board/__manifest__.py
odoo/addons/mail_activity_board/i18n/es.po
odoo/addons/mail_activity_board/i18n/fr.po
odoo/addons/mail_activity_board/i18n/fr_BE.po
odoo/addons/mail_activity_board/i18n/hu.po
odoo/addons/mail_activity_board/i18n/it.po
odoo/addons/mail_activity_board/i18n/mail_activity_board.pot
odoo/addons/mail_activity_board/models/__init__.py
odoo/addons/mail_activity_board/models/mail_activity.py
odoo/addons/mail_activity_board/models/mail_activity_mixin.py
odoo/addons/mail_activity_board/readme/CONTRIBUTORS.rst
odoo/addons/mail_activity_board/readme/DESCRIPTION.rst
odoo/addons/mail_activity_board/readme/USAGE.rst
odoo/addons/mail_activity_board/static/description/icon.png
odoo/addons/mail_activity_board/static/description/index.html
odoo/addons/mail_activity_board/static/src/js/override_chatter.js
odoo/addons/mail_activity_board/static/src/xml/inherit_chatter.xml
odoo/addons/mail_activity_board/tests/__init__.py
odoo/addons/mail_activity_board/tests/test_mail_activity_board.py
odoo/addons/mail_activity_board/views/mail_activity_view.xml
odoo/addons/mail_activity_board/views/templates.xml
odoo13_addon_mail_activity_board-13.0.1.1.0.dist-info/METADATA
odoo13_addon_mail_activity_board-13.0.1.1.0.dist-info/WHEEL
odoo13_addon_mail_activity_board-13.0.1.1.0.dist-info/top_level.txt
odoo13_addon_mail_activity_board-13.0.1.1.0.dist-info/RECORD
